json_serializer/Serializer.py
json_serializer/__init__.py
json_serializer-1.0.1.dist-info/LICENSE
json_serializer-1.0.1.dist-info/METADATA
json_serializer-1.0.1.dist-info/WHEEL
json_serializer-1.0.1.dist-info/top_level.txt
json_serializer-1.0.1.dist-info/RECORD
