Metadata-Version: 2.1
Name: json-serializer
Version: 1.0.1
Summary: The library for serialize/deserialize into format JSON.
Home-page: https://gitlab.com/Chvarkov/json_serializer
Author: Alexey Chvarkov
Author-email: chvarkov.alexey@gmail.com
License: MIT
Platform: UNKNOWN
